{
  "pod": [
    {
      "id": "c1gmomwyi1hwg9x",
      "source_id": "b94xonentqvrphk",
      "base_id": "p764bdm4dach7af",
      "fk_model_id": "miyern110bb8w23",
      "title": "Id",
      "column_name": "id",
      "uidt": "ID",
      "dt": "int4",
      "np": "11",
      "ns": "0",
      "clen": null,
      "cop": null,
      "pk": true,
      "pv": null,
      "rqd": true,
      "un": false,
      "ct": "int(11)",
      "ai": true,
      "unique": null,
      "cdf": null,
      "cc": null,
      "csn": null,
      "dtx": "integer",
      "dtxp": "11",
      "dtxs": "",
      "au": null,
      "validate": null,
      "virtual": null,
      "deleted": null,
      "system": null,
      "order": 1,
      "created_at": "2026-03-08 06:45:57+00:00",
      "updated_at": "2026-03-08 06:45:57+00:00",
      "meta": {
        "defaultViewColOrder": 2,
        "defaultViewColVisibility": true
      },
      "description": null,
      "readonly": false,
      "custom_index_name": null
    },
    {
      "id": "c7l04l27o3s2myx",
      "source_id": "b94xonentqvrphk",
      "base_id": "p764bdm4dach7af",
      "fk_model_id": "miyern110bb8w23",
      "title": "CreatedAt",
      "column_name": "created_at",
      "uidt": "CreatedTime",
      "dt": "timestamp",
      "np": null,
      "ns": null,
      "clen": "45",
      "cop": null,
      "pk": false,
      "pv": null,
      "rqd": false,
      "un": false,
      "ct": "timestamp",
      "ai": false,
      "unique": null,
      "cdf": null,
      "cc": null,
      "csn": null,
      "dtx": "specificType",
      "dtxp": "",
      "dtxs": "",
      "au": null,
      "validate": null,
      "virtual": null,
      "deleted": null,
      "system": true,
      "order": 2,
      "created_at": "2026-03-08 06:45:57+00:00",
      "updated_at": "2026-03-08 06:45:57+00:00",
      "meta": {
        "defaultViewColOrder": 3,
        "defaultViewColVisibility": true
      },
      "description": null,
      "readonly": false,
      "custom_index_name": null
    },
    {
      "id": "co3s8tsapotnj3n",
      "source_id": "b94xonentqvrphk",
      "base_id": "p764bdm4dach7af",
      "fk_model_id": "miyern110bb8w23",
      "title": "UpdatedAt",
      "column_name": "updated_at",
      "uidt": "LastModifiedTime",
      "dt": "timestamp",
      "np": null,
      "ns": null,
      "clen": "45",
      "cop": null,
      "pk": false,
      "pv": null,
      "rqd": false,
      "un": false,
      "ct": "timestamp",
      "ai": false,
      "unique": null,
      "cdf": null,
      "cc": null,
      "csn": null,
      "dtx": "specificType",
      "dtxp": "",
      "dtxs": "",
      "au": null,
      "validate": null,
      "virtual": null,
      "deleted": null,
      "system": true,
      "order": 3,
      "created_at": "2026-03-08 06:45:57+00:00",
      "updated_at": "2026-03-08 06:45:57+00:00",
      "meta": {
        "defaultViewColOrder": 4,
        "defaultViewColVisibility": true
      },
      "description": null,
      "readonly": false,
      "custom_index_name": null
    },
    {
      "id": "cqbb1mgle8ggdd8",
      "source_id": "b94xonentqvrphk",
      "base_id": "p764bdm4dach7af",
      "fk_model_id": "miyern110bb8w23",
      "title": "nc_created_by",
      "column_name": "created_by",
      "uidt": "CreatedBy",
      "dt": "character varying",
      "np": null,
      "ns": null,
      "clen": null,
      "cop": null,
      "pk": false,
      "pv": null,
      "rqd": false,
      "un": false,
      "ct": null,
      "ai": false,
      "unique": null,
      "cdf": null,
      "cc": null,
      "csn": null,
      "dtx": "specificType",
      "dtxp": null,
      "dtxs": null,
      "au": null,
      "validate": null,
      "virtual": null,
      "deleted": null,
      "system": true,
      "order": 4,
      "created_at": "2026-03-08 06:45:57+00:00",
      "updated_at": "2026-03-08 06:45:57+00:00",
      "meta": {
        "defaultViewColOrder": 5,
        "defaultViewColVisibility": true
      },
      "description": null,
      "readonly": false,
      "custom_index_name": null
    },
    {
      "id": "cixj9yjxeard3wj",
      "source_id": "b94xonentqvrphk",
      "base_id": "p764bdm4dach7af",
      "fk_model_id": "miyern110bb8w23",
      "title": "nc_updated_by",
      "column_name": "updated_by",
      "uidt": "LastModifiedBy",
      "dt": "character varying",
      "np": null,
      "ns": null,
      "clen": null,
      "cop": null,
      "pk": false,
      "pv": null,
      "rqd": false,
      "un": false,
      "ct": null,
      "ai": false,
      "unique": null,
      "cdf": null,
      "cc": null,
      "csn": null,
      "dtx": "specificType",
      "dtxp": null,
      "dtxs": null,
      "au": null,
      "validate": null,
      "virtual": null,
      "deleted": null,
      "system": true,
      "order": 5,
      "created_at": "2026-03-08 06:45:57+00:00",
      "updated_at": "2026-03-08 06:45:57+00:00",
      "meta": {
        "defaultViewColOrder": 6,
        "defaultViewColVisibility": true
      },
      "description": null,
      "readonly": false,
      "custom_index_name": null
    },
    {
      "id": "ccsewbssrrydims",
      "source_id": "b94xonentqvrphk",
      "base_id": "p764bdm4dach7af",
      "fk_model_id": "miyern110bb8w23",
      "title": "nc_order",
      "column_name": "nc_order",
      "uidt": "Order",
      "dt": "numeric",
      "np": null,
      "ns": null,
      "clen": null,
      "cop": null,
      "pk": false,
      "pv": null,
      "rqd": false,
      "un": false,
      "ct": null,
      "ai": false,
      "unique": null,
      "cdf": null,
      "cc": null,
      "csn": null,
      "dtx": "specificType",
      "dtxp": null,
      "dtxs": null,
      "au": null,
      "validate": null,
      "virtual": null,
      "deleted": null,
      "system": true,
      "order": 6,
      "created_at": "2026-03-08 06:45:57+00:00",
      "updated_at": "2026-03-08 06:45:57+00:00",
      "meta": {
        "defaultViewColOrder": 7,
        "defaultViewColVisibility": true
      },
      "description": null,
      "readonly": false,
      "custom_index_name": null
    },
    {
      "id": "clyzlwfl9tyef5n",
      "source_id": "b94xonentqvrphk",
      "base_id": "p764bdm4dach7af",
      "fk_model_id": "miyern110bb8w23",
      "title": "PODetailID",
      "column_name": "PODetailID",
      "uidt": "SingleLineText",
      "dt": "text",
      "np": null,
      "ns": null,
      "clen": null,
      "cop": null,
      "pk": false,
      "pv": true,
      "rqd": false,
      "un": false,
      "ct": null,
      "ai": false,
      "unique": null,
      "cdf": null,
      "cc": null,
      "csn": null,
      "dtx": "specificType",
      "dtxp": "",
      "dtxs": " ",
      "au": null,
      "validate": "",
      "virtual": null,
      "deleted": null,
      "system": null,
      "order": 7,
      "created_at": "2026-03-08 06:45:57+00:00",
      "updated_at": "2026-03-08 10:04:56+00:00",
      "meta": {
        "defaultViewColOrder": 1,
        "defaultViewColVisibility": true
      },
      "description": null,
      "readonly": false,
      "custom_index_name": null
    },
    {
      "id": "c529f33qjmm9y40",
      "source_id": "b94xonentqvrphk",
      "base_id": "p764bdm4dach7af",
      "fk_model_id": "miyern110bb8w23",
      "title": "OrderedQty",
      "column_name": "OrderedQty",
      "uidt": "Number",
      "dt": "bigint",
      "np": null,
      "ns": null,
      "clen": null,
      "cop": null,
      "pk": false,
      "pv": null,
      "rqd": false,
      "un": false,
      "ct": null,
      "ai": false,
      "unique": null,
      "cdf": null,
      "cc": null,
      "csn": null,
      "dtx": "specificType",
      "dtxp": "",
      "dtxs": " ",
      "au": null,
      "validate": null,
      "virtual": null,
      "deleted": null,
      "system": false,
      "order": 10,
      "created_at": "2026-03-08 06:47:22+00:00",
      "updated_at": "2026-03-08 06:47:22+00:00",
      "meta": {
        "isLocaleString": false,
        "defaultViewColOrder": 10,
        "defaultViewColVisibility": true
      },
      "description": null,
      "readonly": false,
      "custom_index_name": null
    },
    {
      "id": "c0a89mlgwrn2jqx",
      "source_id": "b94xonentqvrphk",
      "base_id": "p764bdm4dach7af",
      "fk_model_id": "miyern110bb8w23",
      "title": "UnitPrice",
      "column_name": "UnitPrice",
      "uidt": "Number",
      "dt": "bigint",
      "np": null,
      "ns": null,
      "clen": null,
      "cop": null,
      "pk": false,
      "pv": null,
      "rqd": false,
      "un": false,
      "ct": null,
      "ai": false,
      "unique": null,
      "cdf": null,
      "cc": null,
      "csn": null,
      "dtx": "specificType",
      "dtxp": "",
      "dtxs": " ",
      "au": null,
      "validate": null,
      "virtual": null,
      "deleted": null,
      "system": false,
      "order": 11,
      "created_at": "2026-03-08 06:47:22+00:00",
      "updated_at": "2026-03-08 06:47:22+00:00",
      "meta": {
        "isLocaleString": false,
        "defaultViewColOrder": 11,
        "defaultViewColVisibility": true
      },
      "description": null,
      "readonly": false,
      "custom_index_name": null
    },
    {
      "id": "cnmkmgbq2kv9seb",
      "source_id": "b94xonentqvrphk",
      "base_id": "p764bdm4dach7af",
      "fk_model_id": "miyern110bb8w23",
      "title": "Products_id",
      "column_name": "Products_id",
      "uidt": "ForeignKey",
      "dt": "int4",
      "np": null,
      "ns": null,
      "clen": null,
      "cop": null,
      "pk": false,
      "pv": null,
      "rqd": false,
      "un": false,
      "ct": null,
      "ai": false,
      "unique": null,
      "cdf": null,
      "cc": null,
      "csn": null,
      "dtx": null,
      "dtxp": "11",
      "dtxs": "",
      "au": null,
      "validate": null,
      "virtual": null,
      "deleted": null,
      "system": false,
      "order": 12,
      "created_at": "2026-03-08 16:37:11+00:00",
      "updated_at": "2026-03-08 16:37:11+00:00",
      "meta": {
        "defaultViewColOrder": 12,
        "defaultViewColVisibility": true
      },
      "description": null,
      "readonly": false,
      "custom_index_name": null
    },
    {
      "id": "c8rnvhglagvibgh",
      "source_id": "b94xonentqvrphk",
      "base_id": "p764bdm4dach7af",
      "fk_model_id": "miyern110bb8w23",
      "title": "Products",
      "column_name": null,
      "uidt": "LinkToAnotherRecord",
      "dt": null,
      "np": null,
      "ns": null,
      "clen": null,
      "cop": null,
      "pk": null,
      "pv": null,
      "rqd": null,
      "un": null,
      "ct": null,
      "ai": null,
      "unique": null,
      "cdf": null,
      "cc": null,
      "csn": null,
      "dtx": null,
      "dtxp": null,
      "dtxs": null,
      "au": null,
      "validate": null,
      "virtual": true,
      "deleted": null,
      "system": false,
      "order": 13,
      "created_at": "2026-03-08 16:37:11+00:00",
      "updated_at": "2026-03-08 16:37:11+00:00",
      "meta": {
        "custom": false,
        "defaultViewColOrder": 13,
        "defaultViewColVisibility": true
      },
      "description": null,
      "readonly": false,
      "custom_index_name": null,
      "colOptions": {
        "virtual": true,
        "id": "lsxpybixb3akfbx",
        "ref_db_alias": null,
        "type": "bt",
        "db_type": null,
        "fk_column_id": "c8rnvhglagvibgh",
        "fk_related_model_id": "m4cznh4wdhp1pgy",
        "fk_child_column_id": "cnmkmgbq2kv9seb",
        "fk_parent_column_id": "c61n7ylf5oeepic",
        "fk_mm_model_id": null,
        "fk_mm_child_column_id": null,
        "fk_mm_parent_column_id": null,
        "ur": null,
        "dr": null,
        "fk_index_name": null,
        "deleted": null,
        "created_at": "2026-03-08 16:37:11+00:00",
        "updated_at": "2026-03-08 16:37:11+00:00",
        "fk_target_view_id": null,
        "base_id": "p764bdm4dach7af",
        "fk_related_base_id": null,
        "fk_mm_base_id": null,
        "fk_related_source_id": null,
        "fk_mm_source_id": null
      }
    },
    {
      "id": "ccoxkmkoipchrmn",
      "source_id": "b94xonentqvrphk",
      "base_id": "p764bdm4dach7af",
      "fk_model_id": "miyern110bb8w23",
      "title": "Purchase_Orders_id",
      "column_name": "Purchase_Orders_id",
      "uidt": "ForeignKey",
      "dt": "int4",
      "np": null,
      "ns": null,
      "clen": null,
      "cop": null,
      "pk": false,
      "pv": null,
      "rqd": false,
      "un": false,
      "ct": null,
      "ai": false,
      "unique": null,
      "cdf": null,
      "cc": null,
      "csn": null,
      "dtx": null,
      "dtxp": "11",
      "dtxs": "",
      "au": null,
      "validate": null,
      "virtual": null,
      "deleted": null,
      "system": false,
      "order": 14,
      "created_at": "2026-03-08 17:02:23+00:00",
      "updated_at": "2026-03-08 17:02:23+00:00",
      "meta": {
        "defaultViewColOrder": 14,
        "defaultViewColVisibility": true
      },
      "description": null,
      "readonly": false,
      "custom_index_name": null
    },
    {
      "id": "cs8c5mpsr38am6x",
      "source_id": "b94xonentqvrphk",
      "base_id": "p764bdm4dach7af",
      "fk_model_id": "miyern110bb8w23",
      "title": "Purchase_Orders",
      "column_name": null,
      "uidt": "LinkToAnotherRecord",
      "dt": null,
      "np": null,
      "ns": null,
      "clen": null,
      "cop": null,
      "pk": null,
      "pv": null,
      "rqd": null,
      "un": null,
      "ct": null,
      "ai": null,
      "unique": null,
      "cdf": null,
      "cc": null,
      "csn": null,
      "dtx": null,
      "dtxp": null,
      "dtxs": null,
      "au": null,
      "validate": null,
      "virtual": true,
      "deleted": null,
      "system": false,
      "order": 15,
      "created_at": "2026-03-08 17:02:23+00:00",
      "updated_at": "2026-03-08 17:02:23+00:00",
      "meta": {
        "custom": false,
        "defaultViewColOrder": 15,
        "defaultViewColVisibility": true
      },
      "description": null,
      "readonly": false,
      "custom_index_name": null,
      "colOptions": {
        "virtual": true,
        "id": "ly6jvi167jhoo44",
        "ref_db_alias": null,
        "type": "bt",
        "db_type": null,
        "fk_column_id": "cs8c5mpsr38am6x",
        "fk_related_model_id": "m5u0dkeh3cx11zh",
        "fk_child_column_id": "ccoxkmkoipchrmn",
        "fk_parent_column_id": "cmit8km4a24lusw",
        "fk_mm_model_id": null,
        "fk_mm_child_column_id": null,
        "fk_mm_parent_column_id": null,
        "ur": null,
        "dr": null,
        "fk_index_name": null,
        "deleted": null,
        "created_at": "2026-03-08 17:02:23+00:00",
        "updated_at": "2026-03-08 17:02:23+00:00",
        "fk_target_view_id": null,
        "base_id": "p764bdm4dach7af",
        "fk_related_base_id": null,
        "fk_mm_base_id": null,
        "fk_related_source_id": null,
        "fk_mm_source_id": null
      }
    }
  ],
  "gr": [
    {
      "id": "cy4ufb3q62x2zoe",
      "source_id": "b94xonentqvrphk",
      "base_id": "p764bdm4dach7af",
      "fk_model_id": "m738u03fvi1ywi1",
      "title": "Id",
      "column_name": "id",
      "uidt": "ID",
      "dt": "int4",
      "np": "11",
      "ns": "0",
      "clen": null,
      "cop": null,
      "pk": true,
      "pv": null,
      "rqd": true,
      "un": false,
      "ct": "int(11)",
      "ai": true,
      "unique": null,
      "cdf": null,
      "cc": null,
      "csn": null,
      "dtx": "integer",
      "dtxp": "11",
      "dtxs": "",
      "au": null,
      "validate": null,
      "virtual": null,
      "deleted": null,
      "system": null,
      "order": 1,
      "created_at": "2026-03-07 16:18:51+00:00",
      "updated_at": "2026-03-07 16:18:51+00:00",
      "meta": {
        "defaultViewColOrder": 3,
        "defaultViewColVisibility": true
      },
      "description": null,
      "readonly": false,
      "custom_index_name": null
    },
    {
      "id": "cet4gmy0qwelzyl",
      "source_id": "b94xonentqvrphk",
      "base_id": "p764bdm4dach7af",
      "fk_model_id": "m738u03fvi1ywi1",
      "title": "CreatedAt",
      "column_name": "created_at",
      "uidt": "CreatedTime",
      "dt": "timestamp",
      "np": null,
      "ns": null,
      "clen": "45",
      "cop": null,
      "pk": false,
      "pv": null,
      "rqd": false,
      "un": false,
      "ct": "timestamp",
      "ai": false,
      "unique": null,
      "cdf": null,
      "cc": null,
      "csn": null,
      "dtx": "specificType",
      "dtxp": "",
      "dtxs": "",
      "au": null,
      "validate": null,
      "virtual": null,
      "deleted": null,
      "system": true,
      "order": 2,
      "created_at": "2026-03-07 16:18:51+00:00",
      "updated_at": "2026-03-07 16:18:51+00:00",
      "meta": {
        "defaultViewColOrder": 4,
        "defaultViewColVisibility": true
      },
      "description": null,
      "readonly": false,
      "custom_index_name": null
    },
    {
      "id": "cize4voaxbpg2sm",
      "source_id": "b94xonentqvrphk",
      "base_id": "p764bdm4dach7af",
      "fk_model_id": "m738u03fvi1ywi1",
      "title": "UpdatedAt",
      "column_name": "updated_at",
      "uidt": "LastModifiedTime",
      "dt": "timestamp",
      "np": null,
      "ns": null,
      "clen": "45",
      "cop": null,
      "pk": false,
      "pv": null,
      "rqd": false,
      "un": false,
      "ct": "timestamp",
      "ai": false,
      "unique": null,
      "cdf": null,
      "cc": null,
      "csn": null,
      "dtx": "specificType",
      "dtxp": "",
      "dtxs": "",
      "au": null,
      "validate": null,
      "virtual": null,
      "deleted": null,
      "system": true,
      "order": 3,
      "created_at": "2026-03-07 16:18:51+00:00",
      "updated_at": "2026-03-07 16:18:51+00:00",
      "meta": {
        "defaultViewColOrder": 5,
        "defaultViewColVisibility": true
      },
      "description": null,
      "readonly": false,
      "custom_index_name": null
    },
    {
      "id": "c4hb5ccoywsmdpd",
      "source_id": "b94xonentqvrphk",
      "base_id": "p764bdm4dach7af",
      "fk_model_id": "m738u03fvi1ywi1",
      "title": "nc_created_by",
      "column_name": "created_by",
      "uidt": "CreatedBy",
      "dt": "character varying",
      "np": null,
      "ns": null,
      "clen": null,
      "cop": null,
      "pk": false,
      "pv": null,
      "rqd": false,
      "un": false,
      "ct": null,
      "ai": false,
      "unique": null,
      "cdf": null,
      "cc": null,
      "csn": null,
      "dtx": "specificType",
      "dtxp": null,
      "dtxs": null,
      "au": null,
      "validate": null,
      "virtual": null,
      "deleted": null,
      "system": true,
      "order": 4,
      "created_at": "2026-03-07 16:18:51+00:00",
      "updated_at": "2026-03-07 16:18:51+00:00",
      "meta": {
        "defaultViewColOrder": 6,
        "defaultViewColVisibility": true
      },
      "description": null,
      "readonly": false,
      "custom_index_name": null
    },
    {
      "id": "cmz3av2iwr9c239",
      "source_id": "b94xonentqvrphk",
      "base_id": "p764bdm4dach7af",
      "fk_model_id": "m738u03fvi1ywi1",
      "title": "nc_updated_by",
      "column_name": "updated_by",
      "uidt": "LastModifiedBy",
      "dt": "character varying",
      "np": null,
      "ns": null,
      "clen": null,
      "cop": null,
      "pk": false,
      "pv": null,
      "rqd": false,
      "un": false,
      "ct": null,
      "ai": false,
      "unique": null,
      "cdf": null,
      "cc": null,
      "csn": null,
      "dtx": "specificType",
      "dtxp": null,
      "dtxs": null,
      "au": null,
      "validate": null,
      "virtual": null,
      "deleted": null,
      "system": true,
      "order": 5,
      "created_at": "2026-03-07 16:18:51+00:00",
      "updated_at": "2026-03-07 16:18:51+00:00",
      "meta": {
        "defaultViewColOrder": 7,
        "defaultViewColVisibility": true
      },
      "description": null,
      "readonly": false,
      "custom_index_name": null
    },
    {
      "id": "crvwgfafsc20x34",
      "source_id": "b94xonentqvrphk",
      "base_id": "p764bdm4dach7af",
      "fk_model_id": "m738u03fvi1ywi1",
      "title": "nc_order",
      "column_name": "nc_order",
      "uidt": "Order",
      "dt": "numeric",
      "np": null,
      "ns": null,
      "clen": null,
      "cop": null,
      "pk": false,
      "pv": null,
      "rqd": false,
      "un": false,
      "ct": null,
      "ai": false,
      "unique": null,
      "cdf": null,
      "cc": null,
      "csn": null,
      "dtx": "specificType",
      "dtxp": null,
      "dtxs": null,
      "au": null,
      "validate": null,
      "virtual": null,
      "deleted": null,
      "system": true,
      "order": 6,
      "created_at": "2026-03-07 16:18:51+00:00",
      "updated_at": "2026-03-07 16:18:51+00:00",
      "meta": {
        "defaultViewColOrder": 8,
        "defaultViewColVisibility": true
      },
      "description": null,
      "readonly": false,
      "custom_index_name": null
    },
    {
      "id": "c7n7ec0kx8olsx2",
      "source_id": "b94xonentqvrphk",
      "base_id": "p764bdm4dach7af",
      "fk_model_id": "m738u03fvi1ywi1",
      "title": "ReceiptID",
      "column_name": "ReceiptID",
      "uidt": "SingleLineText",
      "dt": "TEXT",
      "np": null,
      "ns": null,
      "clen": null,
      "cop": null,
      "pk": false,
      "pv": true,
      "rqd": false,
      "un": false,
      "ct": null,
      "ai": false,
      "unique": null,
      "cdf": null,
      "cc": null,
      "csn": null,
      "dtx": "specificType",
      "dtxp": "",
      "dtxs": "",
      "au": null,
      "validate": null,
      "virtual": null,
      "deleted": null,
      "system": null,
      "order": 7,
      "created_at": "2026-03-07 16:18:51+00:00",
      "updated_at": "2026-03-07 16:22:15+00:00",
      "meta": {
        "defaultViewColOrder": 1,
        "defaultViewColVisibility": true
      },
      "description": null,
      "readonly": false,
      "custom_index_name": null
    },
    {
      "id": "cnp2jjkkvqsp6v2",
      "source_id": "b94xonentqvrphk",
      "base_id": "p764bdm4dach7af",
      "fk_model_id": "m738u03fvi1ywi1",
      "title": "ReceiptDate",
      "column_name": "ReceiptDate",
      "uidt": "Date",
      "dt": "date",
      "np": null,
      "ns": null,
      "clen": null,
      "cop": null,
      "pk": false,
      "pv": null,
      "rqd": false,
      "un": false,
      "ct": null,
      "ai": false,
      "unique": null,
      "cdf": null,
      "cc": null,
      "csn": null,
      "dtx": "specificType",
      "dtxp": "",
      "dtxs": " ",
      "au": null,
      "validate": null,
      "virtual": null,
      "deleted": null,
      "system": false,
      "order": 10,
      "created_at": "2026-03-07 16:22:15+00:00",
      "updated_at": "2026-03-07 16:22:15+00:00",
      "meta": {
        "date_format": "YYYY-MM-DD",
        "defaultViewColOrder": 10,
        "defaultViewColVisibility": true
      },
      "description": null,
      "readonly": false,
      "custom_index_name": null
    },
    {
      "id": "ctlzddmlncsw8z5",
      "source_id": "b94xonentqvrphk",
      "base_id": "p764bdm4dach7af",
      "fk_model_id": "m738u03fvi1ywi1",
      "title": "Description",
      "column_name": "Description",
      "uidt": "LongText",
      "dt": "text",
      "np": null,
      "ns": null,
      "clen": null,
      "cop": null,
      "pk": false,
      "pv": null,
      "rqd": false,
      "un": false,
      "ct": null,
      "ai": false,
      "unique": null,
      "cdf": null,
      "cc": null,
      "csn": null,
      "dtx": "specificType",
      "dtxp": "",
      "dtxs": " ",
      "au": null,
      "validate": null,
      "virtual": null,
      "deleted": null,
      "system": false,
      "order": 11,
      "created_at": "2026-03-07 16:22:15+00:00",
      "updated_at": "2026-03-07 16:22:15+00:00",
      "meta": {
        "defaultViewColOrder": 11,
        "defaultViewColVisibility": true
      },
      "description": null,
      "readonly": false,
      "custom_index_name": null
    },
    {
      "id": "c4syov831ce629u",
      "source_id": "b94xonentqvrphk",
      "base_id": "p764bdm4dach7af",
      "fk_model_id": "m738u03fvi1ywi1",
      "title": "Users_id",
      "column_name": "Users_id",
      "uidt": "ForeignKey",
      "dt": "int4",
      "np": null,
      "ns": null,
      "clen": null,
      "cop": null,
      "pk": false,
      "pv": null,
      "rqd": false,
      "un": false,
      "ct": null,
      "ai": false,
      "unique": null,
      "cdf": null,
      "cc": null,
      "csn": null,
      "dtx": null,
      "dtxp": "11",
      "dtxs": "",
      "au": null,
      "validate": null,
      "virtual": null,
      "deleted": null,
      "system": false,
      "order": 14,
      "created_at": "2026-03-08 08:19:49+00:00",
      "updated_at": "2026-03-08 08:19:49+00:00",
      "meta": {
        "defaultViewColOrder": 14,
        "defaultViewColVisibility": true
      },
      "description": null,
      "readonly": false,
      "custom_index_name": null
    },
    {
      "id": "c8kqddg4ngg49xx",
      "source_id": "b94xonentqvrphk",
      "base_id": "p764bdm4dach7af",
      "fk_model_id": "m738u03fvi1ywi1",
      "title": "Users",
      "column_name": null,
      "uidt": "LinkToAnotherRecord",
      "dt": null,
      "np": null,
      "ns": null,
      "clen": null,
      "cop": null,
      "pk": null,
      "pv": null,
      "rqd": null,
      "un": null,
      "ct": null,
      "ai": null,
      "unique": null,
      "cdf": null,
      "cc": null,
      "csn": null,
      "dtx": null,
      "dtxp": null,
      "dtxs": null,
      "au": null,
      "validate": null,
      "virtual": true,
      "deleted": null,
      "system": false,
      "order": 15,
      "created_at": "2026-03-08 08:19:49+00:00",
      "updated_at": "2026-03-08 08:19:49+00:00",
      "meta": {
        "custom": false,
        "defaultViewColOrder": 9.5,
        "defaultViewColVisibility": true
      },
      "description": null,
      "readonly": false,
      "custom_index_name": null,
      "colOptions": {
        "virtual": true,
        "id": "l3ycz38imhgpint",
        "ref_db_alias": null,
        "type": "bt",
        "db_type": null,
        "fk_column_id": "c8kqddg4ngg49xx",
        "fk_related_model_id": "mm1izhsiixh0ix2",
        "fk_child_column_id": "c4syov831ce629u",
        "fk_parent_column_id": "cy4j92zymgl8rlb",
        "fk_mm_model_id": null,
        "fk_mm_child_column_id": null,
        "fk_mm_parent_column_id": null,
        "ur": null,
        "dr": null,
        "fk_index_name": null,
        "deleted": null,
        "created_at": "2026-03-08 08:19:49+00:00",
        "updated_at": "2026-03-08 08:19:49+00:00",
        "fk_target_view_id": null,
        "base_id": "p764bdm4dach7af",
        "fk_related_base_id": null,
        "fk_mm_base_id": null,
        "fk_related_source_id": null,
        "fk_mm_source_id": null
      }
    },
    {
      "id": "cmwab09gs7nqh4a",
      "source_id": "b94xonentqvrphk",
      "base_id": "p764bdm4dach7af",
      "fk_model_id": "m738u03fvi1ywi1",
      "title": "Purchase_Orders_id",
      "column_name": "Purchase_Orders_id",
      "uidt": "ForeignKey",
      "dt": "int4",
      "np": null,
      "ns": null,
      "clen": null,
      "cop": null,
      "pk": false,
      "pv": null,
      "rqd": false,
      "un": false,
      "ct": null,
      "ai": false,
      "unique": null,
      "cdf": null,
      "cc": null,
      "csn": null,
      "dtx": null,
      "dtxp": "11",
      "dtxs": "",
      "au": null,
      "validate": null,
      "virtual": null,
      "deleted": null,
      "system": false,
      "order": 16,
      "created_at": "2026-03-08 17:02:23+00:00",
      "updated_at": "2026-03-08 17:02:23+00:00",
      "meta": {
        "defaultViewColOrder": 15,
        "defaultViewColVisibility": true
      },
      "description": null,
      "readonly": false,
      "custom_index_name": null
    },
    {
      "id": "clk0f1evjqlnxjx",
      "source_id": "b94xonentqvrphk",
      "base_id": "p764bdm4dach7af",
      "fk_model_id": "m738u03fvi1ywi1",
      "title": "Purchase_Orders",
      "column_name": null,
      "uidt": "LinkToAnotherRecord",
      "dt": null,
      "np": null,
      "ns": null,
      "clen": null,
      "cop": null,
      "pk": null,
      "pv": null,
      "rqd": null,
      "un": null,
      "ct": null,
      "ai": null,
      "unique": null,
      "cdf": null,
      "cc": null,
      "csn": null,
      "dtx": null,
      "dtxp": null,
      "dtxs": null,
      "au": null,
      "validate": null,
      "virtual": true,
      "deleted": null,
      "system": false,
      "order": 17,
      "created_at": "2026-03-08 17:02:23+00:00",
      "updated_at": "2026-03-08 17:02:23+00:00",
      "meta": {
        "custom": false,
        "defaultViewColOrder": 16,
        "defaultViewColVisibility": true
      },
      "description": null,
      "readonly": false,
      "custom_index_name": null,
      "colOptions": {
        "virtual": true,
        "id": "l6dmwctfzsrlma9",
        "ref_db_alias": null,
        "type": "bt",
        "db_type": null,
        "fk_column_id": "clk0f1evjqlnxjx",
        "fk_related_model_id": "m5u0dkeh3cx11zh",
        "fk_child_column_id": "cmwab09gs7nqh4a",
        "fk_parent_column_id": "cmit8km4a24lusw",
        "fk_mm_model_id": null,
        "fk_mm_child_column_id": null,
        "fk_mm_parent_column_id": null,
        "ur": null,
        "dr": null,
        "fk_index_name": null,
        "deleted": null,
        "created_at": "2026-03-08 17:02:23+00:00",
        "updated_at": "2026-03-08 17:02:23+00:00",
        "fk_target_view_id": null,
        "base_id": "p764bdm4dach7af",
        "fk_related_base_id": null,
        "fk_mm_base_id": null,
        "fk_related_source_id": null,
        "fk_mm_source_id": null
      }
    },
    {
      "id": "c477knsnz35p060",
      "source_id": "b94xonentqvrphk",
      "base_id": "p764bdm4dach7af",
      "fk_model_id": "m738u03fvi1ywi1",
      "title": "Receipt_Details",
      "column_name": null,
      "uidt": "Links",
      "dt": null,
      "np": null,
      "ns": null,
      "clen": null,
      "cop": null,
      "pk": null,
      "pv": null,
      "rqd": null,
      "un": null,
      "ct": null,
      "ai": null,
      "unique": null,
      "cdf": null,
      "cc": null,
      "csn": null,
      "dtx": null,
      "dtxp": null,
      "dtxs": null,
      "au": null,
      "validate": null,
      "virtual": true,
      "deleted": null,
      "system": null,
      "order": 18,
      "created_at": "2026-03-08 17:03:58+00:00",
      "updated_at": "2026-03-08 17:03:58+00:00",
      "meta": {
        "plural": "Receipt_Details",
        "singular": "Receipt_Detail",
        "custom": false,
        "defaultViewColOrder": 17,
        "defaultViewColVisibility": false
      },
      "description": null,
      "readonly": false,
      "custom_index_name": null,
      "colOptions": {
        "virtual": true,
        "id": "lxrsbemo2uvvqzn",
        "ref_db_alias": null,
        "type": "hm",
        "db_type": null,
        "fk_column_id": "c477knsnz35p060",
        "fk_related_model_id": "mpayfc3xf9bypov",
        "fk_child_column_id": "c0s79yzwlgttmqn",
        "fk_parent_column_id": "cy4ufb3q62x2zoe",
        "fk_mm_model_id": null,
        "fk_mm_child_column_id": null,
        "fk_mm_parent_column_id": null,
        "ur": null,
        "dr": null,
        "fk_index_name": null,
        "deleted": null,
        "created_at": "2026-03-08 17:03:58+00:00",
        "updated_at": "2026-03-08 17:03:58+00:00",
        "fk_target_view_id": null,
        "base_id": "p764bdm4dach7af",
        "fk_related_base_id": null,
        "fk_mm_base_id": null,
        "fk_related_source_id": null,
        "fk_mm_source_id": null,
        "rollup_function": "count"
      }
    }
  ],
  "rd": [
    {
      "id": "cpffeh44276ctsd",
      "source_id": "b94xonentqvrphk",
      "base_id": "p764bdm4dach7af",
      "fk_model_id": "mpayfc3xf9bypov",
      "title": "Id",
      "column_name": "id",
      "uidt": "ID",
      "dt": "int4",
      "np": "11",
      "ns": "0",
      "clen": null,
      "cop": null,
      "pk": true,
      "pv": null,
      "rqd": true,
      "un": false,
      "ct": "int(11)",
      "ai": true,
      "unique": null,
      "cdf": null,
      "cc": null,
      "csn": null,
      "dtx": "integer",
      "dtxp": "11",
      "dtxs": "",
      "au": null,
      "validate": null,
      "virtual": null,
      "deleted": null,
      "system": null,
      "order": 1,
      "created_at": "2026-03-07 16:22:53+00:00",
      "updated_at": "2026-03-07 16:22:53+00:00",
      "meta": {
        "defaultViewColOrder": 2,
        "defaultViewColVisibility": true
      },
      "description": null,
      "readonly": false,
      "custom_index_name": null
    },
    {
      "id": "ckj40gt6zec1e3w",
      "source_id": "b94xonentqvrphk",
      "base_id": "p764bdm4dach7af",
      "fk_model_id": "mpayfc3xf9bypov",
      "title": "CreatedAt",
      "column_name": "created_at",
      "uidt": "CreatedTime",
      "dt": "timestamp",
      "np": null,
      "ns": null,
      "clen": "45",
      "cop": null,
      "pk": false,
      "pv": null,
      "rqd": false,
      "un": false,
      "ct": "timestamp",
      "ai": false,
      "unique": null,
      "cdf": null,
      "cc": null,
      "csn": null,
      "dtx": "specificType",
      "dtxp": "",
      "dtxs": "",
      "au": null,
      "validate": null,
      "virtual": null,
      "deleted": null,
      "system": true,
      "order": 2,
      "created_at": "2026-03-07 16:22:53+00:00",
      "updated_at": "2026-03-07 16:22:53+00:00",
      "meta": {
        "defaultViewColOrder": 3,
        "defaultViewColVisibility": true
      },
      "description": null,
      "readonly": false,
      "custom_index_name": null
    },
    {
      "id": "c386oxn9sseg2pm",
      "source_id": "b94xonentqvrphk",
      "base_id": "p764bdm4dach7af",
      "fk_model_id": "mpayfc3xf9bypov",
      "title": "UpdatedAt",
      "column_name": "updated_at",
      "uidt": "LastModifiedTime",
      "dt": "timestamp",
      "np": null,
      "ns": null,
      "clen": "45",
      "cop": null,
      "pk": false,
      "pv": null,
      "rqd": false,
      "un": false,
      "ct": "timestamp",
      "ai": false,
      "unique": null,
      "cdf": null,
      "cc": null,
      "csn": null,
      "dtx": "specificType",
      "dtxp": "",
      "dtxs": "",
      "au": null,
      "validate": null,
      "virtual": null,
      "deleted": null,
      "system": true,
      "order": 3,
      "created_at": "2026-03-07 16:22:53+00:00",
      "updated_at": "2026-03-07 16:22:53+00:00",
      "meta": {
        "defaultViewColOrder": 4,
        "defaultViewColVisibility": true
      },
      "description": null,
      "readonly": false,
      "custom_index_name": null
    },
    {
      "id": "ckbzud2vc8ktb6c",
      "source_id": "b94xonentqvrphk",
      "base_id": "p764bdm4dach7af",
      "fk_model_id": "mpayfc3xf9bypov",
      "title": "nc_created_by",
      "column_name": "created_by",
      "uidt": "CreatedBy",
      "dt": "character varying",
      "np": null,
      "ns": null,
      "clen": null,
      "cop": null,
      "pk": false,
      "pv": null,
      "rqd": false,
      "un": false,
      "ct": null,
      "ai": false,
      "unique": null,
      "cdf": null,
      "cc": null,
      "csn": null,
      "dtx": "specificType",
      "dtxp": null,
      "dtxs": null,
      "au": null,
      "validate": null,
      "virtual": null,
      "deleted": null,
      "system": true,
      "order": 4,
      "created_at": "2026-03-07 16:22:53+00:00",
      "updated_at": "2026-03-07 16:22:53+00:00",
      "meta": {
        "defaultViewColOrder": 5,
        "defaultViewColVisibility": true
      },
      "description": null,
      "readonly": false,
      "custom_index_name": null
    },
    {
      "id": "cnlm246hyy18dhn",
      "source_id": "b94xonentqvrphk",
      "base_id": "p764bdm4dach7af",
      "fk_model_id": "mpayfc3xf9bypov",
      "title": "nc_updated_by",
      "column_name": "updated_by",
      "uidt": "LastModifiedBy",
      "dt": "character varying",
      "np": null,
      "ns": null,
      "clen": null,
      "cop": null,
      "pk": false,
      "pv": null,
      "rqd": false,
      "un": false,
      "ct": null,
      "ai": false,
      "unique": null,
      "cdf": null,
      "cc": null,
      "csn": null,
      "dtx": "specificType",
      "dtxp": null,
      "dtxs": null,
      "au": null,
      "validate": null,
      "virtual": null,
      "deleted": null,
      "system": true,
      "order": 5,
      "created_at": "2026-03-07 16:22:53+00:00",
      "updated_at": "2026-03-07 16:22:53+00:00",
      "meta": {
        "defaultViewColOrder": 6,
        "defaultViewColVisibility": true
      },
      "description": null,
      "readonly": false,
      "custom_index_name": null
    },
    {
      "id": "ceusjjkujjjfc7o",
      "source_id": "b94xonentqvrphk",
      "base_id": "p764bdm4dach7af",
      "fk_model_id": "mpayfc3xf9bypov",
      "title": "nc_order",
      "column_name": "nc_order",
      "uidt": "Order",
      "dt": "numeric",
      "np": null,
      "ns": null,
      "clen": null,
      "cop": null,
      "pk": false,
      "pv": null,
      "rqd": false,
      "un": false,
      "ct": null,
      "ai": false,
      "unique": null,
      "cdf": null,
      "cc": null,
      "csn": null,
      "dtx": "specificType",
      "dtxp": null,
      "dtxs": null,
      "au": null,
      "validate": null,
      "virtual": null,
      "deleted": null,
      "system": true,
      "order": 6,
      "created_at": "2026-03-07 16:22:53+00:00",
      "updated_at": "2026-03-07 16:22:53+00:00",
      "meta": {
        "defaultViewColOrder": 7,
        "defaultViewColVisibility": true
      },
      "description": null,
      "readonly": false,
      "custom_index_name": null
    },
    {
      "id": "ca3v01qyjac2p96",
      "source_id": "b94xonentqvrphk",
      "base_id": "p764bdm4dach7af",
      "fk_model_id": "mpayfc3xf9bypov",
      "title": "DetailID",
      "column_name": "DetailID",
      "uidt": "SingleLineText",
      "dt": "text",
      "np": null,
      "ns": null,
      "clen": null,
      "cop": null,
      "pk": false,
      "pv": true,
      "rqd": false,
      "un": false,
      "ct": null,
      "ai": false,
      "unique": null,
      "cdf": null,
      "cc": null,
      "csn": null,
      "dtx": "specificType",
      "dtxp": "",
      "dtxs": " ",
      "au": null,
      "validate": "",
      "virtual": null,
      "deleted": null,
      "system": null,
      "order": 7,
      "created_at": "2026-03-07 16:22:53+00:00",
      "updated_at": "2026-03-08 10:05:11+00:00",
      "meta": {
        "defaultViewColOrder": 1,
        "defaultViewColVisibility": true
      },
      "description": null,
      "readonly": false,
      "custom_index_name": null
    },
    {
      "id": "cv8k62fkwf7l4az",
      "source_id": "b94xonentqvrphk",
      "base_id": "p764bdm4dach7af",
      "fk_model_id": "mpayfc3xf9bypov",
      "title": "BatchID",
      "column_name": null,
      "uidt": "LinkToAnotherRecord",
      "dt": null,
      "np": null,
      "ns": null,
      "clen": null,
      "cop": null,
      "pk": null,
      "pv": null,
      "rqd": null,
      "un": null,
      "ct": null,
      "ai": null,
      "unique": null,
      "cdf": null,
      "cc": null,
      "csn": null,
      "dtx": null,
      "dtxp": null,
      "dtxs": null,
      "au": null,
      "validate": null,
      "virtual": true,
      "deleted": null,
      "system": null,
      "order": 9,
      "created_at": "2026-03-07 16:27:04+00:00",
      "updated_at": "2026-03-07 16:27:04+00:00",
      "meta": {
        "plural": "Batches",
        "singular": "Batch",
        "custom": false,
        "defaultViewColOrder": 7.75,
        "defaultViewColVisibility": true
      },
      "description": null,
      "readonly": false,
      "custom_index_name": null,
      "colOptions": {
        "virtual": true,
        "id": "l4b6suqmvoz17xr",
        "ref_db_alias": null,
        "type": "oo",
        "db_type": null,
        "fk_column_id": "cv8k62fkwf7l4az",
        "fk_related_model_id": "m8r83f9zdxzz56y",
        "fk_child_column_id": "c0vcqttuf0zaau1",
        "fk_parent_column_id": "cpffeh44276ctsd",
        "fk_mm_model_id": null,
        "fk_mm_child_column_id": null,
        "fk_mm_parent_column_id": null,
        "ur": null,
        "dr": null,
        "fk_index_name": null,
        "deleted": null,
        "created_at": "2026-03-07 16:27:04+00:00",
        "updated_at": "2026-03-07 16:27:04+00:00",
        "fk_target_view_id": null,
        "base_id": "p764bdm4dach7af",
        "fk_related_base_id": null,
        "fk_mm_base_id": null,
        "fk_related_source_id": null,
        "fk_mm_source_id": null
      }
    },
    {
      "id": "cbntjs7k58ozia7",
      "source_id": "b94xonentqvrphk",
      "base_id": "p764bdm4dach7af",
      "fk_model_id": "mpayfc3xf9bypov",
      "title": "ActualQty",
      "column_name": "ActualQty",
      "uidt": "Number",
      "dt": "bigint",
      "np": null,
      "ns": null,
      "clen": null,
      "cop": null,
      "pk": false,
      "pv": null,
      "rqd": false,
      "un": false,
      "ct": null,
      "ai": false,
      "unique": null,
      "cdf": null,
      "cc": null,
      "csn": null,
      "dtx": "specificType",
      "dtxp": "",
      "dtxs": " ",
      "au": null,
      "validate": null,
      "virtual": null,
      "deleted": null,
      "system": false,
      "order": 10,
      "created_at": "2026-03-07 16:27:04+00:00",
      "updated_at": "2026-03-07 16:27:04+00:00",
      "meta": {
        "isLocaleString": false,
        "defaultViewColOrder": 8,
        "defaultViewColVisibility": true
      },
      "description": null,
      "readonly": false,
      "custom_index_name": null
    },
    {
      "id": "cg6ket2dki90fv8",
      "source_id": "b94xonentqvrphk",
      "base_id": "p764bdm4dach7af",
      "fk_model_id": "mpayfc3xf9bypov",
      "title": "UnitPrice",
      "column_name": "UnitPrice",
      "uidt": "Decimal",
      "dt": "decimal",
      "np": null,
      "ns": null,
      "clen": null,
      "cop": null,
      "pk": false,
      "pv": null,
      "rqd": false,
      "un": false,
      "ct": null,
      "ai": false,
      "unique": null,
      "cdf": null,
      "cc": null,
      "csn": null,
      "dtx": "specificType",
      "dtxp": "",
      "dtxs": "2",
      "au": null,
      "validate": null,
      "virtual": null,
      "deleted": null,
      "system": false,
      "order": 11,
      "created_at": "2026-03-07 16:27:04+00:00",
      "updated_at": "2026-03-07 16:27:04+00:00",
      "meta": {
        "precision": 1,
        "isLocaleString": false,
        "defaultViewColOrder": 10,
        "defaultViewColVisibility": true
      },
      "description": null,
      "readonly": false,
      "custom_index_name": null
    },
    {
      "id": "c0s79yzwlgttmqn",
      "source_id": "b94xonentqvrphk",
      "base_id": "p764bdm4dach7af",
      "fk_model_id": "mpayfc3xf9bypov",
      "title": "Goods_Receipts_id",
      "column_name": "Goods_Receipts_id",
      "uidt": "ForeignKey",
      "dt": "int4",
      "np": null,
      "ns": null,
      "clen": null,
      "cop": null,
      "pk": false,
      "pv": null,
      "rqd": false,
      "un": false,
      "ct": null,
      "ai": false,
      "unique": null,
      "cdf": null,
      "cc": null,
      "csn": null,
      "dtx": null,
      "dtxp": "11",
      "dtxs": "",
      "au": null,
      "validate": null,
      "virtual": null,
      "deleted": null,
      "system": false,
      "order": 12,
      "created_at": "2026-03-08 17:03:58+00:00",
      "updated_at": "2026-03-08 17:03:58+00:00",
      "meta": {
        "defaultViewColOrder": 11,
        "defaultViewColVisibility": true
      },
      "description": null,
      "readonly": false,
      "custom_index_name": null
    },
    {
      "id": "c8zivxy7fljbuvj",
      "source_id": "b94xonentqvrphk",
      "base_id": "p764bdm4dach7af",
      "fk_model_id": "mpayfc3xf9bypov",
      "title": "Goods_Receipts",
      "column_name": null,
      "uidt": "LinkToAnotherRecord",
      "dt": null,
      "np": null,
      "ns": null,
      "clen": null,
      "cop": null,
      "pk": null,
      "pv": null,
      "rqd": null,
      "un": null,
      "ct": null,
      "ai": null,
      "unique": null,
      "cdf": null,
      "cc": null,
      "csn": null,
      "dtx": null,
      "dtxp": null,
      "dtxs": null,
      "au": null,
      "validate": null,
      "virtual": true,
      "deleted": null,
      "system": false,
      "order": 13,
      "created_at": "2026-03-08 17:03:58+00:00",
      "updated_at": "2026-03-08 17:03:58+00:00",
      "meta": {
        "custom": false,
        "defaultViewColOrder": 12,
        "defaultViewColVisibility": true
      },
      "description": null,
      "readonly": false,
      "custom_index_name": null,
      "colOptions": {
        "virtual": true,
        "id": "leio5ks3jz0vkxw",
        "ref_db_alias": null,
        "type": "bt",
        "db_type": null,
        "fk_column_id": "c8zivxy7fljbuvj",
        "fk_related_model_id": "m738u03fvi1ywi1",
        "fk_child_column_id": "c0s79yzwlgttmqn",
        "fk_parent_column_id": "cy4ufb3q62x2zoe",
        "fk_mm_model_id": null,
        "fk_mm_child_column_id": null,
        "fk_mm_parent_column_id": null,
        "ur": null,
        "dr": null,
        "fk_index_name": null,
        "deleted": null,
        "created_at": "2026-03-08 17:03:58+00:00",
        "updated_at": "2026-03-08 17:03:58+00:00",
        "fk_target_view_id": null,
        "base_id": "p764bdm4dach7af",
        "fk_related_base_id": null,
        "fk_mm_base_id": null,
        "fk_related_source_id": null,
        "fk_mm_source_id": null
      }
    }
  ]
}